helpers/__init__.py
helpers/__main__.py
helpers/all_files_in_directory.py
helpers/files.py
helpers/haversine_distance.py
cimren_helpers-1.0.3.dist-info/METADATA
cimren_helpers-1.0.3.dist-info/WHEEL
cimren_helpers-1.0.3.dist-info/top_level.txt
cimren_helpers-1.0.3.dist-info/RECORD
