Metadata-Version: 2.1
Name: cimren-helpers
Version: 1.0.3
Summary: Helper functions
Home-page: https://github.com/emrahcimren/helper_functions
Author: cimren
Author-email: cimren.1@gmail.com
License: MIT
Platform: UNKNOWN
Classifier: License :: OSI Approved :: MIT License
Classifier: Programming Language :: Python :: 3
Classifier: Programming Language :: Python :: 3.6
Requires-Dist: Pathlib
Requires-Dist: numpy
